relu/__init__.py
relu/cli.py
relu/core/__init__.py
relu/core/aiResponse.py
relu/core/types/__init__.py
relu/core/types/assistant.py
relu/core/types/prompt.py
relu/utils/__init__.py
relu/utils/configOperations.py
relu/utils/parseResponseMD.py
relu/utils/printer.py
relu/utils/processArgs.py
reluai-1.2.6.dist-info/LICENSE
reluai-1.2.6.dist-info/METADATA
reluai-1.2.6.dist-info/WHEEL
reluai-1.2.6.dist-info/entry_points.txt
reluai-1.2.6.dist-info/top_level.txt
reluai-1.2.6.dist-info/RECORD
