Metadata-Version: 2.1
Name: reluai
Version: 1.2.6
Summary: A command-line assistant powered by Gemini AI to enhance productivity
Home-page: https://github.com/techatlasdev/relu-cli
Author: Giovanny Jimenez
Author-email: gjimenezdeza@gmail.com
Project-URL: Bug Tracker, https://github.com/techatlasdev/relu-cli/issues
Project-URL: Documentation, https://github.com/techatlasdev/relu-cli#readme
Project-URL: Source Code, https://github.com/techatlasdev/relu-cli
Keywords: LLM,API,assistant,gemini,google,data,python,cli,ReLU,AI,Gemini AI
Classifier: Development Status :: 5 - Production/Stable
Classifier: Intended Audience :: Developers
Classifier: License :: OSI Approved :: MIT License
Classifier: Natural Language :: English
Classifier: Operating System :: OS Independent
Classifier: Programming Language :: Python
Classifier: Programming Language :: Python :: 3
Classifier: Programming Language :: Python :: 3.6
Classifier: Programming Language :: Python :: 3.7
Classifier: Programming Language :: Python :: 3.8
Classifier: Programming Language :: Python :: 3.9
Classifier: Programming Language :: Python :: 3.10
Classifier: Programming Language :: Python :: 3.11
Classifier: Topic :: Software Development :: Libraries :: Python Modules
Classifier: Topic :: Scientific/Engineering :: Artificial Intelligence
Requires-Python: >=3.6
License-File: LICENSE
Requires-Dist: requests >=2.25.1
Requires-Dist: google-generativeai
